README.rst
setup.py
transformers_model/__init__.py
transformers_model/_tokenize_vec.py
transformers_model/classifier.py
transformers_model/collator.py
transformers_model/dataset.py
transformers_model/utils.py
transformers_model.egg-info/PKG-INFO
transformers_model.egg-info/SOURCES.txt
transformers_model.egg-info/dependency_links.txt
transformers_model.egg-info/not-zip-safe
transformers_model.egg-info/requires.txt
transformers_model.egg-info/top_level.txt