Metadata-Version: 2.1
Name: transformers-model
Version: 0.2.3
Summary: Model hub for transformers.
Home-page: https://gitee.com/summry/torch-model-hub
Author: summy
Author-email: fkfkfk2024@2925.com
License: UNKNOWN
Keywords: Pytorch,AI,Machine learning,Deep learning,Bert,llm,transformers
Platform: UNKNOWN
Requires-Python: >=3.6
